rpa_aliexpress/__init__.py
rpa_aliexpress/api/__init__.py
rpa_aliexpress/command/__init__.py
rpa_aliexpress/command/bill/__init__.py
rpa_aliexpress/command/bill/service/__init__.py
rpa_aliexpress/request/__init__.py
rpa_aliexpress/service/__init__.py
rpa_aliexpress-1.0.0.dist-info/LICENSE
rpa_aliexpress-1.0.0.dist-info/METADATA
rpa_aliexpress-1.0.0.dist-info/WHEEL
rpa_aliexpress-1.0.0.dist-info/top_level.txt
rpa_aliexpress-1.0.0.dist-info/RECORD
